korwordextract/__init__.py
korwordextract/noun_extractor.py
korwordextract-0.0.1.dist-info/METADATA
korwordextract-0.0.1.dist-info/RECORD
korwordextract-0.0.1.dist-info/WHEEL
korwordextract-0.0.1.dist-info/top_level.txt
