Metadata-Version: 2.1
Name: korwordextract
Version: 0.0.1
Summary: To extract Korean words
Home-page: UNKNOWN
Author: Sang Yup Lee
Author-email: sangyuplee@yonsei.ac.kr
License: UNKNOWN
Platform: UNKNOWN
Classifier: Programming Language :: Python :: 3
Classifier: License :: OSI Approved :: MIT License
Classifier: Operating System :: OS Independent
